{
  "ats_key": "oracle",
  "company_name_for_postings": "Fixture Oracle",
  "company": {
    "company_name": "Fixture Oracle",
    "company_url": "https://example.oraclecloud.com/hcmUI/CandidateExperience/en/sites/CX_1/requisitions",
    "ATS_name": "Oracle"
  },
  "config": {
    "siteBaseUrl": "https://example.oraclecloud.com",
    "language": "en",
    "siteNumber": "CX_1",
    "boardUrl": "https://example.oraclecloud.com/hcmUI/CandidateExperience/en/sites/CX_1/requisitions"
  },
  "raw_response": {
    "items": [
      {
        "requisitionList": [
          {
            "Id": "REQ-1001",
            "Title": "Principal Cloud Engineer",
            "PostedDate": "2026-05-06T08:00:00+03:00",
            "Department": "Engineering",
            "WorkplaceType": "Remote",
            "workLocation": [
              {
                "TownOrCity": "Istanbul",
                "Country": "Turkiye"
              }
            ]
          }
        ]
      }
    ]
  },
  "expected": [
    {
      "ats_key": "oracle",
      "company_name": "Fixture Oracle",
      "position_name": "Principal Cloud Engineer",
      "job_posting_url": "https://example.oraclecloud.com/hcmUI/CandidateExperience/en/sites/CX_1/job/REQ-1001",
      "country": "Turkey",
      "remote_type": "remote",
      "industry": "Engineering",
      "is_remote": true
    }
  ]
}
